auto_package_installer/__init__.py
auto_package_installer/base_os_manager.py
auto_package_installer/factory.py
auto_package_installer/linux_dependency_manager.py
auto_package_installer/windows_dependency_manager.py
auto_package_installer-0.1.3.dist-info/LICENSE
auto_package_installer-0.1.3.dist-info/METADATA
auto_package_installer-0.1.3.dist-info/WHEEL
auto_package_installer-0.1.3.dist-info/top_level.txt
auto_package_installer-0.1.3.dist-info/RECORD
