Metadata-Version: 2.1
Name: auto-package-installer
Version: 0.1.3
Summary: A package to auto install requirements.txt file into a virtual environment
Home-page: 
Author: Slurrps Mcgee
Author-email: your.email@example.com
Classifier: Programming Language :: Python :: 3
Classifier: License :: OSI Approved :: MIT License
Classifier: Operating System :: OS Independent
Requires-Python: >=3.12
License-File: LICENSE
